CHANGES.txt
LICENSE.txt
MANIFEST.in
README.rst
setup.cfg
setup.py
django_versioned_static_url/__init__.py
django_versioned_static_url.egg-info/PKG-INFO
django_versioned_static_url.egg-info/SOURCES.txt
django_versioned_static_url.egg-info/dependency_links.txt
django_versioned_static_url.egg-info/requires.txt
django_versioned_static_url.egg-info/top_level.txt
django_versioned_static_url/templatetags/__init__.py
django_versioned_static_url/templatetags/versioned_static.py