Metadata-Version: 1.0
Name: django-versioned-static-url
Version: 0.2
Summary: A template tag for generating a URL for a static file, with a version string which will be effectively unique based on the contents of the file.
Home-page: https://github.com/ubuntudesign/django-versioned-static-url
Author: Robin
Author-email: robin.winslow@canonical.com
License: UNKNOWN
Platform: UNKNOWN
